napari_gruvbox/__init__.py
napari_gruvbox/_version.py
napari_gruvbox/napari.yaml
napari_gruvbox/_tests/__init__.py
napari_gruvbox-0.1.2.dist-info/licenses/LICENSE
napari_gruvbox-0.1.2.dist-info/METADATA
napari_gruvbox-0.1.2.dist-info/WHEEL
napari_gruvbox-0.1.2.dist-info/entry_points.txt
napari_gruvbox-0.1.2.dist-info/top_level.txt
napari_gruvbox-0.1.2.dist-info/RECORD
