Metadata-Version: 2.4
Name: napari-gruvbox
Version: 0.1.2
Summary: Gruvbox theme for napari.
Home-page: https://github.com/brisvag/napari-gruvbox
Author: Lorenzo Gaifas
Author-email: brisvag@gmail.com
License: 
Project-URL: Bug Tracker, https://github.com/brisvag/napari-gruvbox/issues
Project-URL: Documentation, https://github.com/brisvag/napari-gruvbox#README.md
Project-URL: Source Code, https://github.com/brisvag/napari-gruvbox
Project-URL: User Support, https://github.com/brisvag/napari-gruvbox/issues
Classifier: Development Status :: 2 - Pre-Alpha
Classifier: Framework :: napari
Classifier: Intended Audience :: Developers
Classifier: License :: OSI Approved :: GNU Lesser General Public License v3 (LGPLv3)
Classifier: Operating System :: OS Independent
Classifier: Programming Language :: Python
Classifier: Programming Language :: Python :: 3
Classifier: Programming Language :: Python :: 3 :: Only
Classifier: Programming Language :: Python :: 3.10
Classifier: Programming Language :: Python :: 3.11
Classifier: Programming Language :: Python :: 3.12
Classifier: Programming Language :: Python :: 3.13
Classifier: Topic :: Scientific/Engineering :: Image Processing
Requires-Python: >=3.10
License-File: LICENSE
Requires-Dist: numpy
Provides-Extra: all
Requires-Dist: napari[all]; extra == "all"
Dynamic: license-file
